samanage/__init__.py
samanage/__version__.py
samanage/comments.py
samanage/connection.py
samanage/incidents.py
samanage/samanage.py
samanage/sites.py
samanage/users.py
samanage/api/__init__.py
samanage/api/sites.py
samanage/utils/__init__.py
samanage/utils/utils.py
samanage_py-0.1.8.dist-info/LICENSE
samanage_py-0.1.8.dist-info/METADATA
samanage_py-0.1.8.dist-info/WHEEL
samanage_py-0.1.8.dist-info/top_level.txt
samanage_py-0.1.8.dist-info/RECORD
