Metadata-Version: 2.1
Name: samanage-py
Version: 0.1.8
Summary: A package to easily connect to Samanage API
Home-page: https://github.com/rodneymandap/samanage-py
Author: Rodney Jan Mandap
Author-email: rodneyjan.mandap@gmail.com
License: UNKNOWN
Platform: UNKNOWN
Classifier: Development Status :: 3 - Alpha
Classifier: Intended Audience :: Developers
Classifier: Natural Language :: English
Classifier: Programming Language :: Python :: 3
Classifier: Operating System :: OS Independent
Requires-Python: >=3.6
Requires-Dist: requests
